tgcf_hello
